yapo/__init__.py
yapo/obfuscator.py
yapo/techniques/__init__.py
yapo/techniques/base64/__init__.py
yapo/techniques/base64/main.py
yapo/techniques/codesplit/__init__.py
yapo/techniques/codesplit/main.py
yapo/techniques/codesplit/test.py
yapo/techniques/decomment/__init__.py
yapo/techniques/decomment/main.py
yapo/techniques/decomment/test.py
yapo/techniques/string_encrypt/__init__.py
yapo/techniques/string_encrypt/main.py
YAPythonObfuscator-0.0.4.dist-info/LICENSE
YAPythonObfuscator-0.0.4.dist-info/METADATA
YAPythonObfuscator-0.0.4.dist-info/WHEEL
YAPythonObfuscator-0.0.4.dist-info/top_level.txt
YAPythonObfuscator-0.0.4.dist-info/RECORD
